aframexr/__init__.py
aframexr/test.py
aframexr/api/__init__.py
aframexr/api/components.py
aframexr/api/data.py
aframexr/api/encoding.py
aframexr/api/filters.py
aframexr/utils/__init__.py
aframexr/utils/axis_html_creator.py
aframexr/utils/chart_creator.py
aframexr/utils/charts_html_creator.py
aframexr/utils/constants.py
aframexr/utils/scene_creator.py
aframexr-2025.11.16.2.dist-info/METADATA
aframexr-2025.11.16.2.dist-info/WHEEL
aframexr-2025.11.16.2.dist-info/top_level.txt
aframexr-2025.11.16.2.dist-info/RECORD
