Metadata-Version: 2.4
Name: aframexr
Version: 2025.11.16.2
Summary: Python library to visualize data in Virtual and Extended Reality using Aframe components.
Author: David Díaz
Project-URL: Documentation, https://davidlab20.github.io/TFG/
Project-URL: Source, https://github.com/davidlab20/TFG/
Requires-Python: >=3.12
